rest_vlc.py
rest_vlc-1.6.1.dist-info/LICENSE
rest_vlc-1.6.1.dist-info/METADATA
rest_vlc-1.6.1.dist-info/WHEEL
rest_vlc-1.6.1.dist-info/top_level.txt
rest_vlc-1.6.1.dist-info/RECORD
