Metadata-Version: 2.1
Name: rest-vlc
Version: 1.6.1
Summary: A Python library for controlling VLC media player via REST API
Home-page: https://github.com/timelessnesses/rest-vlc
Author: Rukchad Wongprayoon
Author-email: contact@biomooping.tk
License: MIT
Platform: UNKNOWN
Classifier: Programming Language :: Python :: 3
Classifier: Operating System :: OS Independent
Requires-Python: >=3
License-File: LICENSE
Requires-Dist: requests
Requires-Dist: xmltodict
Provides-Extra: async
Requires-Dist: aiohttp[speedups] ; extra == 'async'
Requires-Dist: uvloop ; (sys_platform == "linux") and extra == 'async'
Provides-Extra: build
Requires-Dist: build ; extra == 'build'
Requires-Dist: wheel ; extra == 'build'
Provides-Extra: dev
Requires-Dist: pytest ; extra == 'dev'
Requires-Dist: python-dotenv ; extra == 'dev'
Provides-Extra: publish
Requires-Dist: twine ; extra == 'publish'
Requires-Dist: wheel ; extra == 'publish'
